[
{
    "id": 1,
    "homeTeam": "Chelsea",
    "awayTeam": "Copenhagen",
    "date": "2025-03-13",
    "time": "20:00",
    "insight": "Chelsea to Win by at Least Two Goals",
    "odds": "1.75",
    "confidence": "90%",
    "analysis": "Chelsea's impeccable form in the Europa Conference League and their home advantage suggest a dominant performance against Copenhagen.",
    "bookmaker": {
      "name": "1xBet",
      "logo": "https://raw.githubusercontent.com/derekkipkemoi/SmartScoreAnalysis.com/refs/heads/main/1xbet-logo.svg",
      "link": "https://www.1xbet.com"
    }
  },
  {
    "id": 2,
    "homeTeam": "Rangers",
    "awayTeam": "Fenerbahce",
    "date": "2025-03-13",
    "time": "20:00",
    "insight": "Rangers to Win & Both Teams to Score",
    "odds": "2.10",
    "confidence": "85%",
    "analysis": "Holding a two-goal advantage, Rangers are poised to progress, but Fenerbahce's attacking threat means both teams are likely to find the net.",
    "bookmaker": {
      "name": "1xBet",
      "logo": "https://raw.githubusercontent.com/derekkipkemoi/SmartScoreAnalysis.com/refs/heads/main/1xbet-logo.svg",
      "link": "https://www.1xbet.com"
    }
  },
  {
    "id": 3,
    "homeTeam": "Lazio",
    "awayTeam": "Viktoria Plzen",
    "date": "2025-03-13",
    "time": "18:45",
    "insight": "Lazio to Win & Under 2.5 Goals",
    "odds": "2.50",
    "confidence": "80%",
    "analysis": "Lazio's solid defense at home suggests a low-scoring victory against Viktoria Plzen.",
    "bookmaker": {
      "name": "1xBet",
      "logo": "https://raw.githubusercontent.com/derekkipkemoi/SmartScoreAnalysis.com/refs/heads/main/1xbet-logo.svg",
      "link": "https://www.1xbet.com"
    }
  },

  {
    "id": 4,
    "homeTeam": "Manchester United",
    "awayTeam": "Real Sociedad",
    "date": "2025-03-13",
    "time": "20:00",
    "insight": "Manchester United to Win & Under 2.5 Goals",
    "odds": "2.10",
    "confidence": "85%",
    "analysis": "After a 1-1 draw in the first leg, Manchester United aims to leverage their home advantage at Old Trafford to secure a narrow victory, with a strong defensive performance expected.",
    "bookmaker": {
      "name": "1xBet",
      "logo": "https://raw.githubusercontent.com/derekkipkemoi/SmartScoreAnalysis.com/refs/heads/main/1xbet-logo.svg",
      "link": "https://www.1xbet.com"
    }
  },
  {
    "id": 5,
    "homeTeam": "Vitória Guimarães",
    "awayTeam": "Real Betis",
    "date": "2025-03-13",
    "time": "21:00",
    "insight": "Vitória Guimarães to Win & Both Teams to Score",
    "odds": "2.50",
    "confidence": "80%",
    "analysis": "With the first leg ending in a 2-2 draw, Vitória Guimarães will look to capitalize on their home advantage to edge out a victory, though Real Betis's attacking prowess suggests both teams are likely to score.",
    "bookmaker": {
      "name": "1xBet",
      "logo": "https://raw.githubusercontent.com/derekkipkemoi/SmartScoreAnalysis.com/refs/heads/main/1xbet-logo.svg",
      "link": "https://www.1xbet.com"
    }
  },
  {
    "id": 6,
    "homeTeam": "Roma",
    "awayTeam": "Bayer Leverkusen",
    "date": "2025-03-13",
    "time": "19:45",
    "insight": "Roma to Win & Over 2.5 Goals",
    "odds": "2.20",
    "confidence": "88%",
    "analysis": "Roma’s attacking depth and home advantage in the Stadio Olimpico should be enough to overcome Bayer Leverkusen in an exciting, high-scoring match.",
    "bookmaker": {
      "name": "1xBet",
      "logo": "https://raw.githubusercontent.com/derekkipkemoi/SmartScoreAnalysis.com/refs/heads/main/1xbet-logo.svg",
      "link": "https://www.1xbet.com"
    }
  },
  {
    "id": 7,
    "homeTeam": "Marseille",
    "awayTeam": "Feyenoord",
    "date": "2025-03-13",
    "time": "20:30",
    "insight": "Draw & Both Teams to Score",
    "odds": "3.00",
    "confidence": "82%",
    "analysis": "A tightly contested match is expected as both teams have been evenly matched, making a draw with goals on both sides the most probable outcome.",
    "bookmaker": {
      "name": "1xBet",
      "logo": "https://raw.githubusercontent.com/derekkipkemoi/SmartScoreAnalysis.com/refs/heads/main/1xbet-logo.svg",
      "link": "https://www.1xbet.com"
    }
  },
  {
    "id": 8,
    "homeTeam": "Tottenham Hotspur",
    "awayTeam": "AC Milan",
    "date": "2025-03-13",
    "time": "20:00",
    "insight": "Tottenham to Win & Both Teams to Score",
    "odds": "2.75",
    "confidence": "80%",
    "analysis": "Tottenham, playing at home, will be motivated to overturn a first-leg deficit. However, AC Milan's attacking capabilities suggest both teams are likely to score.",
    "bookmaker": {
      "name": "1xBet",
      "logo": "https://raw.githubusercontent.com/derekkipkemoi/SmartScoreAnalysis.com/refs/heads/main/1xbet-logo.svg",
      "link": "https://www.1xbet.com"
    }
  },
  {
    "id": 9,
    "homeTeam": "Eintracht Frankfurt",
    "awayTeam": "Ajax",
    "date": "2025-03-13",
    "time": "18:45",
    "insight": "Both Teams to Score & Over 2.5 Goals",
    "odds": "1.90",
    "confidence": "85%",
    "analysis": "Both Eintracht Frankfurt and Ajax have potent offenses, making a high-scoring game with goals from both sides highly probable.",
    "bookmaker": {
      "name": "1xBet",
      "logo": "https://raw.githubusercontent.com/derekkipkemoi/SmartScoreAnalysis.com/refs/heads/main/1xbet-logo.svg",
      "link": "https://www.1xbet.com"
    }
  },
  {
    "id": 10,
    "homeTeam": "Sevilla",
    "awayTeam": "Arsenal",
    "date": "2025-03-13",
    "time": "21:00",
    "insight": "Sevilla to Win & Under 2.5 Goals",
    "odds": "3.20",
    "confidence": "78%",
    "analysis": "Sevilla's strong home form and defensive solidity suggest a low-scoring victory against an Arsenal side struggling with injuries.",
    "bookmaker": {
      "name": "1xBet",
      "logo": "https://raw.githubusercontent.com/derekkipkemoi/SmartScoreAnalysis.com/refs/heads/main/1xbet-logo.svg",
      "link": "https://www.1xbet.com"
    }
  },
  {
    "id": 11,
    "homeTeam": "Fiorentina",
    "awayTeam": "Panathinaikos",
    "date": "2025-03-13",
    "time": "21:00",
    "insight": "Fiorentina to Win & Over 2.5 Goals",
    "odds": "2.00",
    "confidence": "85%",
    "analysis": "Fiorentina's strong home record and attacking prowess suggest a high-scoring victory against Panathinaikos.",
    "bookmaker": {
      "name": "1xBet",
      "logo": "https://raw.githubusercontent.com/derekkipkemoi/SmartScoreAnalysis.com/refs/heads/main/1xbet-logo.svg",
      "link": "https://www.1xbet.com"
    }
  },
  {
    "id": 12,
    "homeTeam": "Cercle Brugge",
    "awayTeam": "Jagiellonia Białystok",
    "date": "2025-03-13",
    "time": "20:00",
    "insight": "Cercle Brugge to Win & Both Teams to Score",
    "odds": "2.50",
    "confidence": "80%",
    "analysis": "Cercle Brugge's home advantage and attacking style make them favorites, though Jagiellonia's offense is likely to find the net.",
    "bookmaker": {
      "name": "1xBet",
      "logo": "https://raw.githubusercontent.com/derekkipkemoi/SmartScoreAnalysis.com/refs/heads/main/1xbet-logo.svg",
      "link": "https://www.1xbet.com"
    }
  },
  {
    "id": 13,
    "homeTeam": "Djurgårdens IF",
    "awayTeam": "Celje",
    "date": "2025-03-13",
    "time": "18:45",
    "insight": "Djurgårdens IF to Win & Under 2.5 Goals",
    "odds": "2.20",
    "confidence": "82%",
    "analysis": "Djurgårdens' defensive solidity at home suggests a low-scoring victory over Celje.",
    "bookmaker": {
      "name": "1xBet",
      "logo": "https://raw.githubusercontent.com/derekkipkemoi/SmartScoreAnalysis.com/refs/heads/main/1xbet-logo.svg",
      "link": "https://www.1xbet.com"
    }
  },
  {
    "id": 14,
    "homeTeam": "Chelsea",
    "awayTeam": "Copenhagen",
    "date": "2025-03-13",
    "time": "20:00",
    "insight": "Chelsea to Win by at least Two Goals",
    "odds": "1.75",
    "confidence": "90%",
    "analysis": "Chelsea's strong performance in the first leg and their impeccable record in the competition make them heavy favorites to secure a comfortable victory at home.",
    "bookmaker": {
      "name": "1xBet",
      "logo": "https://raw.githubusercontent.com/derekkipkemoi/SmartScoreAnalysis.com/refs/heads/main/1xbet-logo.svg",
      "link": "https://www.1xbet.com"
    }
  },
  {
    "id": 15,
    "homeTeam": "Rangers",
    "awayTeam": "Fenerbahce",
    "date": "2025-03-13",
    "time": "20:00",
    "insight": "Rangers to Win & Both Teams to Score",
    "odds": "2.60",
    "confidence": "85%",
    "analysis": "Holding a two-goal lead from the first leg, Rangers are expected to capitalize on their home advantage, though Fenerbahce's attacking threat suggests both teams will find the net.",
    "bookmaker": {
      "name": "1xBet",
      "logo": "https://raw.githubusercontent.com/derekkipkemoi/SmartScoreAnalysis.com/refs/heads/main/1xbet-logo.svg",
      "link": "https://www.1xbet.com"
    }
  }
]
